Metadata-Version: 1.1
Name: Phyme
Version: 0.0.8
Summary: Python rhyming dictionary for songwriting
Home-page: https://github.com/jameswenzel/Phyme
Author: James Wenzel
Author-email: jameswenzel@berkeley.edu
License: MIT License
Download-URL: https://github.com/jameswenzel/Phyme/tarball/0.0.8
Keywords: songwriting,rhyme,rhyming,dictionary,slant,rhymes,song,writing
Platform: UNKNOWN
